{
  "input": {
    "input": "C:\\Users\\flore\\Pictures\\3d",
    "mask": null
  },
  "processing": {
    "simplify_tolerance": 10.0,
    "smooth_iterations": 1,
    "extrude_height": 20.0,
    "min_polygon_dimension": 0,
    "threshold": 128,
    "mask_method": "Alpha"
  },
  "batch": {
    "include_patterns": [
      "*.png",
      "*.jpg",
      "*.jpeg",
      "*.bmp",
      "*.tiff",
      "*.tga"
    ],
    "exclude_patterns": [],
    "workers": 1,
    "continue_on_error": false
  },
  "output": {
    "output_folder": "C:\\Users\\flore\\Pictures\\3d\\output",
    "side_texture": "wood.jpg",
    "back_texture": "wood.jpg",
    "skip_intermediates": false,
    "create_subdirs": true
  }
}